{
  "openapi": "3.0.1",
  "info": {
    "title": "API_HOSOBENHAN",
    "version": "1.0"
  },
  "paths": {
    "/api/NhanVienYTe/List": {
      "get": {
        "tags": [
          "NhanVienYTe"
        ],
        "parameters": [
          {
            "name": "mahsba",
            "in": "query",
            "schema": {
              "type": "string"
            }
          }
        ],
        "responses": {
          "200": {
            "description": "Success"
          }
        }
      }
    },
    "/api/NhanVienYTe/ListQLDonThuoc": {
      "get": {
        "tags": [
          "NhanVienYTe"
        ],
        "parameters": [
          {
            "name": "mahsba",
            "in": "query",
            "schema": {
              "type": "string"
            }
          }
        ],
        "responses": {
          "200": {
            "description": "Success"
          }
        }
      }
    },
    "/api/NhanVienYTe/Thuoc": {
      "get": {
        "tags": [
          "NhanVienYTe"
        ],
        "parameters": [
          {
            "name": "ma",
            "in": "query",
            "schema": {
              "type": "string"
            }
          },
          {
            "name": "mahsba",
            "in": "query",
            "schema": {
              "type": "string"
            }
          }
        ],
        "responses": {
          "200": {
            "description": "Success"
          }
        }
      }
    },
    "/api/NhanVienYTe/ListHoSoBenhAn": {
      "get": {
        "tags": [
          "NhanVienYTe"
        ],
        "responses": {
          "200": {
            "description": "Success"
          }
        }
      }
    },
    "/api/NhanVienYTe/BenhNhan": {
      "get": {
        "tags": [
          "NhanVienYTe"
        ],
        "parameters": [
          {
            "name": "ma",
            "in": "query",
            "schema": {
              "type": "string"
            }
          },
          {
            "name": "mahsba",
            "in": "query",
            "schema": {
              "type": "string"
            }
          }
        ],
        "responses": {
          "200": {
            "description": "Success"
          }
        }
      }
    },
    "/api/NhanVienYTe/HSBenhNhan": {
      "get": {
        "tags": [
          "NhanVienYTe"
        ],
        "responses": {
          "200": {
            "description": "Success"
          }
        }
      }
    },
    "/api/NhanVienYTe/Adddatapcs": {
      "post": {
        "tags": [
          "NhanVienYTe"
        ],
        "requestBody": {
          "content": {
            "application/json": {
              "schema": {
                "$ref": "#/components/schemas/PhieuChamSocMD"
              }
            },
            "text/json": {
              "schema": {
                "$ref": "#/components/schemas/PhieuChamSocMD"
              }
            },
            "application/*+json": {
              "schema": {
                "$ref": "#/components/schemas/PhieuChamSocMD"
              }
            }
          }
        },
        "responses": {
          "200": {
            "description": "Success"
          }
        }
      }
    },
    "/api/NhanVienYTe/ListTaoHoSo": {
      "get": {
        "tags": [
          "NhanVienYTe"
        ],
        "responses": {
          "200": {
            "description": "Success"
          }
        }
      }
    },
    "/api/NhanVienYTe/Timkiemcccd": {
      "post": {
        "tags": [
          "NhanVienYTe"
        ],
        "requestBody": {
          "content": {
            "application/json": {
              "schema": {
                "$ref": "#/components/schemas/TimkiemcccdRequest"
              }
            },
            "text/json": {
              "schema": {
                "$ref": "#/components/schemas/TimkiemcccdRequest"
              }
            },
            "application/*+json": {
              "schema": {
                "$ref": "#/components/schemas/TimkiemcccdRequest"
              }
            }
          }
        },
        "responses": {
          "200": {
            "description": "Success"
          }
        }
      }
    },
    "/api/NhanVienYTe/LocBacSy": {
      "post": {
        "tags": [
          "NhanVienYTe"
        ],
        "requestBody": {
          "content": {
            "application/json": {
              "schema": {
                "$ref": "#/components/schemas/LocBacSyRequest"
              }
            },
            "text/json": {
              "schema": {
                "$ref": "#/components/schemas/LocBacSyRequest"
              }
            },
            "application/*+json": {
              "schema": {
                "$ref": "#/components/schemas/LocBacSyRequest"
              }
            }
          }
        },
        "responses": {
          "200": {
            "description": "Success"
          }
        }
      }
    },
    "/api/NhanVienYTe/CapNhatThongTinBN": {
      "post": {
        "tags": [
          "NhanVienYTe"
        ],
        "requestBody": {
          "content": {
            "application/json": {
              "schema": {
                "$ref": "#/components/schemas/BenhNhan2"
              }
            },
            "text/json": {
              "schema": {
                "$ref": "#/components/schemas/BenhNhan2"
              }
            },
            "application/*+json": {
              "schema": {
                "$ref": "#/components/schemas/BenhNhan2"
              }
            }
          }
        },
        "responses": {
          "200": {
            "description": "Success"
          }
        }
      }
    },
    "/api/NhanVienYTe/QLNB": {
      "get": {
        "tags": [
          "NhanVienYTe"
        ],
        "responses": {
          "200": {
            "description": "Success"
          }
        }
      }
    },
    "/api/NhanVienYTe/TimKiemHoSo": {
      "get": {
        "tags": [
          "NhanVienYTe"
        ],
        "parameters": [
          {
            "name": "tddb",
            "in": "query",
            "schema": {
              "type": "string"
            }
          }
        ],
        "responses": {
          "200": {
            "description": "Success"
          }
        }
      }
    },
    "/api/NhanVienYTe/Addhosobenhnhan": {
      "post": {
        "tags": [
          "NhanVienYTe"
        ],
        "requestBody": {
          "content": {
            "application/json": {
              "schema": {
                "$ref": "#/components/schemas/BenhNhan1"
              }
            },
            "text/json": {
              "schema": {
                "$ref": "#/components/schemas/BenhNhan1"
              }
            },
            "application/*+json": {
              "schema": {
                "$ref": "#/components/schemas/BenhNhan1"
              }
            }
          }
        },
        "responses": {
          "200": {
            "description": "Success"
          }
        }
      }
    },
    "/api/NhanVienYTe/ListHSBenhNhan": {
      "get": {
        "tags": [
          "NhanVienYTe"
        ],
        "responses": {
          "200": {
            "description": "Success"
          }
        }
      }
    },
    "/api/NhanVienYTe/TimKiemHoSoBN": {
      "get": {
        "tags": [
          "NhanVienYTe"
        ],
        "parameters": [
          {
            "name": "tddb",
            "in": "query",
            "schema": {
              "type": "string"
            }
          }
        ],
        "responses": {
          "200": {
            "description": "Success"
          }
        }
      }
    },
    "/api/ThongKe_ThuNguyet/Year": {
      "get": {
        "tags": [
          "ThongKe_ThuNguyet"
        ],
        "responses": {
          "200": {
            "description": "Success"
          }
        }
      }
    },
    "/api/ThongKe_ThuNguyet/Month": {
      "get": {
        "tags": [
          "ThongKe_ThuNguyet"
        ],
        "parameters": [
          {
            "name": "year",
            "in": "query",
            "schema": {
              "type": "integer",
              "format": "int32"
            }
          }
        ],
        "responses": {
          "200": {
            "description": "Success"
          }
        }
      }
    },
    "/api/ThongKe_ThuNguyet/Date": {
      "get": {
        "tags": [
          "ThongKe_ThuNguyet"
        ],
        "parameters": [
          {
            "name": "month",
            "in": "query",
            "schema": {
              "type": "integer",
              "format": "int32"
            }
          },
          {
            "name": "year",
            "in": "query",
            "schema": {
              "type": "integer",
              "format": "int32"
            }
          }
        ],
        "responses": {
          "200": {
            "description": "Success"
          }
        }
      }
    },
    "/api/ThongKe_ThuNguyet/Top3Khoa": {
      "get": {
        "tags": [
          "ThongKe_ThuNguyet"
        ],
        "responses": {
          "200": {
            "description": "Success"
          }
        }
      }
    },
    "/api/ThongKe_ThuNguyet/ColumnMonth": {
      "get": {
        "tags": [
          "ThongKe_ThuNguyet"
        ],
        "responses": {
          "200": {
            "description": "Success"
          }
        }
      }
    },
    "/api/ThongKe_ThuNguyet/HSBA": {
      "get": {
        "tags": [
          "ThongKe_ThuNguyet"
        ],
        "responses": {
          "200": {
            "description": "Success"
          }
        }
      }
    },
    "/api/ThongKe_ThuNguyet/XetNghiem": {
      "get": {
        "tags": [
          "ThongKe_ThuNguyet"
        ],
        "responses": {
          "200": {
            "description": "Success"
          }
        }
      }
    },
    "/api/ThongKe_ThuNguyet/TaiKham": {
      "get": {
        "tags": [
          "ThongKe_ThuNguyet"
        ],
        "responses": {
          "200": {
            "description": "Success"
          }
        }
      }
    },
    "/api/ThongKe_ThuNguyet/ThongKeNhanSu": {
      "get": {
        "tags": [
          "ThongKe_ThuNguyet"
        ],
        "responses": {
          "200": {
            "description": "Success"
          }
        }
      }
    },
    "/api/ThongKe_ThuNguyet/ThongKeChanDoan": {
      "get": {
        "tags": [
          "ThongKe_ThuNguyet"
        ],
        "responses": {
          "200": {
            "description": "Success"
          }
        }
      }
    },
    "/api/ThongKe_ThuNguyet/SoLuong": {
      "get": {
        "tags": [
          "ThongKe_ThuNguyet"
        ],
        "responses": {
          "200": {
            "description": "Success"
          }
        }
      }
    }
  },
  "components": {
    "schemas": {
      "BenhNhan1": {
        "type": "object",
        "properties": {
          "cccd": {
            "type": "string",
            "nullable": true
          },
          "trieuChung": {
            "type": "string",
            "nullable": true
          },
          "khoa": {
            "type": "string",
            "nullable": true
          }
        },
        "additionalProperties": false
      },
      "BenhNhan2": {
        "type": "object",
        "properties": {
          "mabn": {
            "type": "string",
            "nullable": true
          },
          "doiTuong": {
            "type": "string",
            "nullable": true
          },
          "soBHYT": {
            "type": "string",
            "nullable": true
          },
          "gitriBHYT": {
            "type": "string",
            "format": "date-time",
            "nullable": true
          },
          "hoTenNTNhan": {
            "type": "string",
            "nullable": true
          },
          "diaChiNT": {
            "type": "string",
            "nullable": true
          },
          "sdtntNhan": {
            "type": "string",
            "nullable": true
          }
        },
        "additionalProperties": false
      },
      "LocBacSyRequest": {
        "type": "object",
        "properties": {
          "makhoa": {
            "type": "string",
            "nullable": true
          }
        },
        "additionalProperties": false
      },
      "PhieuChamSocMD": {
        "type": "object",
        "properties": {
          "maHSBA": {
            "type": "string",
            "nullable": true
          },
          "ngay": {
            "type": "string",
            "format": "date-time"
          },
          "dienBienBenh": {
            "type": "string",
            "nullable": true
          },
          "yLenh": {
            "type": "string",
            "nullable": true
          },
          "tenDieuDuong": {
            "type": "string",
            "nullable": true
          }
        },
        "additionalProperties": false
      },
      "TimkiemcccdRequest": {
        "type": "object",
        "properties": {
          "cccd": {
            "type": "string",
            "nullable": true
          }
        },
        "additionalProperties": false
      }
    }
  }
}